lsyflasksdkcore_v1/__init__.py
lsyflasksdkcore_v1/blueprints.py
lsyflasksdkcore_v1/context.py
lsyflasksdkcore_v1/dbresult.py
lsyflasksdkcore_v1/excel.py
lsyflasksdkcore_v1/exceptions.py
lsyflasksdkcore_v1/model.py
lsyflasksdkcore_v1/sae.py
lsyflasksdkcore_v1/schema.py
lsyflasksdkcore_v1/serialization.py
lsyflasksdkcore_v1/sqlalchemy_factory.py
lsyflasksdkcore_v1/decorators/__init__.py
lsyflasksdkcore_v1/export/__init__.py
lsyflasksdkcore_v1/export/csv.py
lsyflasksdkcore_v1/export/xls.py
lsyflasksdkcore_v1/linq/__init__.py
lsyflasksdkcore_v1/linq/core.py
lsyflasksdkcore_v1/linq/linq_exceptions.py
lsyflasksdkcore_v1/logging/__init__.py
lsyflasksdkcore_v1/logging/file_logger.py
lsyflasksdkcore_v1/logging/stash_logger.py
lsyflasksdkcore_v1/swagger/__init__.py
lsyflasksdkcore_v1/swagger/doc.py
lsyflasksdkcore_v1/swagger/plugins.py
lsyflasksdkcore_v1/swagger/test.py
lsyflasksdkcore_v1/utils/__init__.py
lsyflasksdkcore_v1/utils/lazy.py
lsyflasksdkcore_v1/utils/singleton_meta.py
lsyflasksdkcore_v1/utils/sm2encry.py
lsyflasksdkcore_v1/utils/sm2utils.py
lsyflasksdkcore_v1/utils/token_utils.py
lsyflasksdkcore_v1/utils/tree.py
lsyflasksdkcore_v1/utils/unique.py
lsyflasksdkcore_v1-1.0.1.dist-info/licenses/LICENSE
lsyflasksdkcore_v1-1.0.1.dist-info/METADATA
lsyflasksdkcore_v1-1.0.1.dist-info/WHEEL
lsyflasksdkcore_v1-1.0.1.dist-info/top_level.txt
lsyflasksdkcore_v1-1.0.1.dist-info/RECORD
